app/__init__.py
app/main.py
app/models.py
app/operations.py
calculadoraapi_fastapi_breno-0.1.6.dist-info/METADATA
calculadoraapi_fastapi_breno-0.1.6.dist-info/WHEEL
calculadoraapi_fastapi_breno-0.1.6.dist-info/top_level.txt
calculadoraapi_fastapi_breno-0.1.6.dist-info/RECORD
