Metadata-Version: 2.4
Name: calculadoraapi-fastapi-breno
Version: 0.1.6
Summary: Calculadora API utilizando FastAPI
Author: Breno Amâncio
License: MIT
Requires-Python: >=3.9, <=3.12.5
Requires-Dist: fastapi<0.100.0,>=0.95.2
Requires-Dist: pydantic==1.10.7
Requires-Dist: uvicorn==0.22.0
Dynamic: author
Dynamic: license
Dynamic: requires-dist
Dynamic: requires-python
Dynamic: summary
